DiscreteHillClimbing/DiscreteHillClimbing.py
DiscreteHillClimbing/__init__.py
DiscreteHillClimbing/main.py
DiscreteHillClimbing-1.1.0.dist-info/LICENSE
DiscreteHillClimbing-1.1.0.dist-info/METADATA
DiscreteHillClimbing-1.1.0.dist-info/WHEEL
DiscreteHillClimbing-1.1.0.dist-info/top_level.txt
DiscreteHillClimbing-1.1.0.dist-info/RECORD
