Metadata-Version: 2.1
Name: DiscreteHillClimbing
Version: 1.1.0
Summary: An easy python implementation of Hill Climbing algorithm for tasks with discrete variables
Home-page: https://github.com/PasaOpasen/DiscreteHillClimbing
Author: Demetry Pascal
Author-email: qtckpuhdsa@gmail.com
Maintainer: Demetry Pascal
License: UNKNOWN
Keywords: solve,optimization,problem,fast,combinatorial,easy,discrete
Platform: UNKNOWN
Classifier: Programming Language :: Python :: 3.8
Classifier: License :: OSI Approved :: MIT License
Classifier: Operating System :: OS Independent
Classifier: Topic :: Software Development :: Libraries :: Python Modules
License-File: LICENSE
Requires-Dist: numpy
